{
  "/-deb": {
    "component": "c4f5d8e4",
    "config": "5e9f5e1a"
  },
  "/blog-512": {
    "component": "a6aa9e1f",
    "items": [
      {
        "content": "28b429f3"
      },
      {
        "content": "ce200a47"
      },
      {
        "content": "f92a5651"
      },
      {
        "content": "c0114d2b"
      }
    ],
    "metadata": "bbb4ffb5"
  },
  "/blog/tags-3a8": {
    "component": "01a85c17",
    "tags": "8be5b89e"
  },
  "/blog/tags/announcements-e1a": {
    "component": "6875c492",
    "items": [
      {
        "content": "28b429f3"
      },
      {
        "content": "ce200a47"
      },
      {
        "content": "c0114d2b"
      }
    ],
    "metadata": "6d4edb66"
  },
  "/blog/tags/vale-server-c56": {
    "component": "6875c492",
    "items": [
      {
        "content": "28b429f3"
      },
      {
        "content": "ce200a47"
      },
      {
        "content": "f92a5651"
      },
      {
        "content": "c0114d2b"
      }
    ],
    "metadata": "3280f3d3"
  },
  "/blog/vale-server-274": {
    "component": "ccc49370",
    "content": "d31076eb"
  },
  "/blog/vale-server.1.3-3f4": {
    "component": "ccc49370",
    "content": "9bc2db91"
  },
  "/blog/vale-server.1.4-edd": {
    "component": "ccc49370",
    "content": "e1a5f782"
  },
  "/blog/vsintro-8c7": {
    "component": "ccc49370",
    "content": "c622790e"
  },
  "/search-3c1": {
    "component": "e822976c"
  },
  "/-457": {
    "component": "1be78505",
    "docsMetadata": "ec1ed54d"
  },
  "/common/points-72d": {
    "component": "17896441",
    "content": "29f9447b"
  },
  "/vale-server/add-ons/lt-609": {
    "component": "17896441",
    "content": "3040a31d"
  },
  "/vale-server/clients/atom-45e": {
    "component": "17896441",
    "content": "6f94a1cb"
  },
  "/vale-server/clients/chrome-725": {
    "component": "17896441",
    "content": "afa2662a"
  },
  "/vale-server/clients/gdocs-697": {
    "component": "17896441",
    "content": "7afd7bc5"
  },
  "/vale-server/clients/sublime-e85": {
    "component": "17896441",
    "content": "46f80e7f"
  },
  "/vale-server/clients/vscode-c57": {
    "component": "17896441",
    "content": "5ef13e3b"
  },
  "/vale-server/concepts/config-869": {
    "component": "17896441",
    "content": "1c93f7e6"
  },
  "/vale-server/concepts/scoping-883": {
    "component": "17896441",
    "content": "a0400144"
  },
  "/vale-server/concepts/styles-353": {
    "component": "17896441",
    "content": "5dc44763"
  },
  "/vale-server/concepts/syncing-cf1": {
    "component": "17896441",
    "content": "391afe90"
  },
  "/vale-server/concepts/vocab-2ed": {
    "component": "17896441",
    "content": "88f627c4"
  },
  "/vale-server/gui-74f": {
    "component": "17896441",
    "content": "24ab4a08"
  },
  "/vale-server/install-50a": {
    "component": "17896441",
    "content": "46ebc288"
  },
  "/vale-server/integrations/gh-action-59f": {
    "component": "17896441",
    "content": "d3fa4df2"
  },
  "/vale-server/usage-67f": {
    "component": "17896441",
    "content": "1800df44"
  },
  "/vale/about-681": {
    "component": "17896441",
    "content": "dd79d940"
  },
  "/vale/cli-334": {
    "component": "17896441",
    "content": "699ac2d3"
  },
  "/vale/config-e76": {
    "component": "17896441",
    "content": "4bad7742"
  },
  "/vale/install-c18": {
    "component": "17896441",
    "content": "5f97b160"
  },
  "/vale/scoping-79b": {
    "component": "17896441",
    "content": "57c1cf62"
  },
  "/vale/styles-e84": {
    "component": "17896441",
    "content": "75a8267b"
  },
  "/vale/vocab-42c": {
    "component": "17896441",
    "content": "1d7f10cd"
  }
}